jklib/__init__.py
jklib/dj/__init__.py
jklib/dj/admin.py
jklib/dj/decorators.py
jklib/dj/emails.py
jklib/dj/exceptions.py
jklib/dj/files.py
jklib/dj/filters.py
jklib/dj/images.py
jklib/dj/managers.py
jklib/dj/models.py
jklib/dj/network.py
jklib/dj/pagination.py
jklib/dj/permissions.py
jklib/dj/serializers.py
jklib/dj/templates.py
jklib/dj/test_runner.py
jklib/dj/tests.py
jklib/dj/validators.py
jklib/dj/viewsets.py
jklib/meili/__init__.py
jklib/meili/search.py
jklib/meili/types.py
jklib/meili/dj/__init__.py
jklib/meili/dj/indexer.py
jklib/meili/dj/serializers.py
jklib/meili/dj/test_utils.py
jklib/std/__init__.py
jklib/std/decorators.py
jklib/std/files.py
jklib/std/images.py
jklib/std/inputs.py
jklib/std/json.py
jklib/std/maths.py
jklib/std/strings.py
jklib/std/threads.py
jklib/std/transforms.py
jklib-5.2.3.dist-info/LICENCE.txt
jklib-5.2.3.dist-info/METADATA
jklib-5.2.3.dist-info/WHEEL
jklib-5.2.3.dist-info/top_level.txt
jklib-5.2.3.dist-info/RECORD
